{
  "suite_name": "silver_customers",
  "expectations": [
    {
      "type": "expect_column_values_to_not_be_null",
      "kwargs": {
        "column": "customer_id"
      }
    },
    {
      "type": "expect_column_values_to_be_unique",
      "kwargs": {
        "column": "customer_id"
      }
    },
    {
      "type": "expect_column_values_to_be_in_set",
      "kwargs": {
        "column": "segment",
        "value_set": [
          "SMB",
          "MID",
          "ENT"
        ]
      }
    },
    {
      "type": "expect_column_values_to_not_be_null",
      "kwargs": {
        "column": "city"
      }
    }
  ]
}